sum_pts/__init__.py
sum_pts/__main__.py
sum_pts/pt_counter.py
sum_pts-0.0.4.dist-info/METADATA
sum_pts-0.0.4.dist-info/WHEEL
sum_pts-0.0.4.dist-info/RECORD
