Metadata-Version: 2.1
Name: sum-pts
Version: 0.0.4
Summary: counts assignment points
Author: higger
Author-email: matt.higger@gmail.com
Requires-Python: >=3.10,<4.0
Classifier: Programming Language :: Python :: 3
Classifier: Programming Language :: Python :: 3.10
Classifier: Programming Language :: Python :: 3.11
Classifier: Programming Language :: Python :: 3.12
Requires-Dist: pandas (>=2.2.2,<3.0.0)
Requires-Dist: tabulate (>=0.9.0,<0.10.0)
